attacktree/__init__.py
attacktree/models.py
attacktree/renderer.py
attacktree/style.json
attacktree-0.0.191.dist-info/LICENSE
attacktree-0.0.191.dist-info/METADATA
attacktree-0.0.191.dist-info/WHEEL
attacktree-0.0.191.dist-info/top_level.txt
attacktree-0.0.191.dist-info/RECORD
