Metadata-Version: 2.1
Name: attacktree
Version: 0.0.191
Summary: Build, analyize and render attack trees
Home-page: https://github.com/hyakuhei/attackTrees
Author: hyakuhei
Author-email: hyakuhei@gmail.com
License: UNKNOWN
Platform: UNKNOWN
Classifier: Programming Language :: Python :: 3
Classifier: License :: OSI Approved :: Apache Software License
Classifier: Operating System :: OS Independent
Requires-Python: >=3.7
Requires-Dist: graphviz (>=0.16)
